media_identifier/__init__.py
media_identifier/identifier.py
tests/__init__.py
media_identifier_jeisserocha-0.0.2.dist-info/LICENSE
media_identifier_jeisserocha-0.0.2.dist-info/METADATA
media_identifier_jeisserocha-0.0.2.dist-info/WHEEL
media_identifier_jeisserocha-0.0.2.dist-info/top_level.txt
media_identifier_jeisserocha-0.0.2.dist-info/RECORD
