Metadata-Version: 2.1
Name: media-identifier-jeisserocha
Version: 0.0.2
Summary: Package that helps identify what type of content is for a given file ( from MIME officials)
Home-page: https://github.com/Jeisse/content-type-identifier.git
Author: Jeisse Rocha
Author-email: jeisserocha@gmail.com
License: UNKNOWN
Platform: UNKNOWN
Classifier: Programming Language :: Python :: 3
Classifier: License :: OSI Approved :: MIT License
Classifier: Operating System :: OS Independent
Requires-Python: >=3.6
License-File: LICENSE
